ftemplates/__init__.py
ftemplates/available_templates/data_science_notebook.ipynb
ftemplates/cli.py
ftemplates-0.1.10.dist-info/entry_points.txt
ftemplates-0.1.10.dist-info/LICENSE
ftemplates-0.1.10.dist-info/METADATA
ftemplates-0.1.10.dist-info/WHEEL
ftemplates-0.1.10.dist-info/RECORD
