Metadata-Version: 2.1
Name: ftemplates
Version: 0.1.10
Summary: CLI app to create files with templates.
Home-page: https://github.com/smv7/ftemplates
Author: smv7
Author-email: smv7.github@gmail.com
Requires-Python: >=3.10,<4.0
Classifier: Programming Language :: Python :: 3
Classifier: Programming Language :: Python :: 3.10
Classifier: Programming Language :: Python :: 3.11
Requires-Dist: click (>=8.1.3,<9.0.0)
Project-URL: Repository, https://github.com/smv7/ftemplates
